odoo/addons/mail_brand/README.rst
odoo/addons/mail_brand/__init__.py
odoo/addons/mail_brand/__manifest__.py
odoo/addons/mail_brand/controllers/__init__.py
odoo/addons/mail_brand/controllers/binary.py
odoo/addons/mail_brand/controllers/main.py
odoo/addons/mail_brand/data/mail_template.xml
odoo/addons/mail_brand/i18n/it.po
odoo/addons/mail_brand/i18n/mail_brand.pot
odoo/addons/mail_brand/i18n/nl.po
odoo/addons/mail_brand/models/__init__.py
odoo/addons/mail_brand/models/ir_model.py
odoo/addons/mail_brand/models/mail_thread.py
odoo/addons/mail_brand/models/res_brand.py
odoo/addons/mail_brand/readme/CONTEXT.md
odoo/addons/mail_brand/readme/CONTRIBUTORS.md
odoo/addons/mail_brand/readme/CREDITS.md
odoo/addons/mail_brand/readme/DESCRIPTION.md
odoo/addons/mail_brand/readme/ROADMAP.md
odoo/addons/mail_brand/readme/USAGE.md
odoo/addons/mail_brand/static/description/CommunityBadge.png
odoo/addons/mail_brand/static/description/icon.png
odoo/addons/mail_brand/static/description/index.html
odoo/addons/mail_brand/tests/__init__.py
odoo/addons/mail_brand/tests/common.py
odoo/addons/mail_brand/tests/test_brand_controller.py
odoo/addons/mail_brand/tests/test_mail_compose_message.py
odoo/addons/mail_brand/tests/test_res_brand.py
odoo/addons/mail_brand/wizard/__init__.py
odoo/addons/mail_brand/wizard/mail_compose_message.py
odoo/addons/mail_brand/wizard/mail_compose_message_view.xml
odoo_addon_mail_brand-18.0.1.0.0.4.dist-info/METADATA
odoo_addon_mail_brand-18.0.1.0.0.4.dist-info/WHEEL
odoo_addon_mail_brand-18.0.1.0.0.4.dist-info/top_level.txt
odoo_addon_mail_brand-18.0.1.0.0.4.dist-info/RECORD
