Metadata-Version: 2.1
Name: odoo-addon-mail_brand
Version: 18.0.1.0.0.4
Requires-Python: >=3.10
Requires-Dist: odoo-addon-brand==18.0.*
Requires-Dist: odoo==18.0.*
Summary: If a model has a brand defined to it, emails send from this model will be branded accordingly.
Home-page: https://github.com/OCA/brand
License: AGPL-3
Author: Odoo Community Association (OCA), Gert Pellin / Snakebyte Development, bosd
Author-email: support@odoo-community.org
Classifier: Programming Language :: Python
Classifier: Framework :: Odoo
Classifier: Framework :: Odoo :: 18.0
Classifier: License :: OSI Approved :: GNU Affero General Public License v3
